Metadata-Version: 2.1
Name: aithamza-regression-model
Version: 0.0.2
Summary: Example regression model package from Train In Data.
Home-page: https://github.com/aithamza
Author: Moussa Ait Hamza
Author-email: mouassa.aithamza@um6p.ma
License: BSD-3
Platform: UNKNOWN
Classifier: License :: OSI Approved :: MIT License
Classifier: Programming Language :: Python
Classifier: Programming Language :: Python :: 3
Classifier: Programming Language :: Python :: 3.6
Classifier: Programming Language :: Python :: 3.7
Classifier: Programming Language :: Python :: 3.8
Classifier: Programming Language :: Python :: 3.9
Classifier: Programming Language :: Python :: Implementation :: CPython
Classifier: Programming Language :: Python :: Implementation :: PyPy
Requires-Python: >=3.6.0
Requires-Dist: numpy
Requires-Dist: pandas
Requires-Dist: pydantic
Requires-Dist: scikit-learn
Requires-Dist: strictyaml
Requires-Dist: ruamel.yaml
Requires-Dist: feature-engine
Requires-Dist: joblib
